shakelab/__init__.py
shakelab/geolib/__init__.py
shakelab/gmpe/__init__.py
shakelab/gmpe/atkinson_2015.py
shakelab/gmpe/base.py
shakelab/gmpe/bragato_slejko_2005.py
shakelab/gmpe/massa_etal_2008.py
shakelab/hazard/__init__.py
shakelab/hazard/correlation.py
shakelab/hazard/magnitude_frequency_distribution.py
shakelab/hazard/magnitude_scaling.py
shakelab/hazard/catalogue/__init__.py
shakelab/hazard/seismicity/__init__.py
shakelab/hazard/seismicity/magnitude_frequency_distribution.py
shakelab/libutils/__init__.py
shakelab/libutils/ascii.py
shakelab/libutils/constants.py
shakelab/libutils/geodetic.py
shakelab/libutils/time.py
shakelab/libutils/utils.py
shakelab/modeling/__init__.py
shakelab/modeling/source.py
shakelab/modeling/gmpe/__init__.py
shakelab/modeling/gmpe/atkinson_2015.py
shakelab/modeling/gmpe/base.py
shakelab/modeling/gmpe/bragato_slejko_2005.py
shakelab/modeling/gmpe/massa_etal_2008.py
shakelab/seismicity/__init__.py
shakelab/seismicity/catalogue.py
shakelab/seismicity/parsers.py
shakelab/seismicity/seismicity.py
shakelab/signals/__init__.py
shakelab/signals/ascii.py
shakelab/signals/base.py
shakelab/signals/fourier.py
shakelab/signals/io.py
shakelab/signals/mseed.py
shakelab/signals/mseed_BK.py
shakelab/signals/mseed_copy.py
shakelab/signals/parser.py
shakelab/signals/response.py
shakelab/signals/sac.py
shakelab/signals/seedlink.py
shakelab/signals/seg.py
shakelab/signals/smdb.py
shakelab/signals/waveform.py
shakelab/site/__init__.py
shakelab/site/engpar.py
shakelab/site/graphics.py
shakelab/site/response.py
shakelab/site/sitedb.py
shakelab/site/soil.py
shakelab/specmod/__init__.py
shakelab/specmod/source.py
shakelab/structures/__init__.py
shakelab/structures/fragility.py
shakelab/structures/oqutils.py
shakelab/structures/response.py
shakelab/utils/__init__.py
shakelab/utils/time.py
shakelab/utils/utils.py
tests/__init__.py
tests/site/__init__.py
tests/site/test_response.py
tests/site/test_soil.py
shakelab-0.0.1.dist-info/LICENSE
shakelab-0.0.1.dist-info/METADATA
shakelab-0.0.1.dist-info/WHEEL
shakelab-0.0.1.dist-info/top_level.txt
shakelab-0.0.1.dist-info/RECORD
