Metadata-Version: 2.1
Name: shakelab
Version: 0.0.1
Summary: Python tools for engineering seismology
Home-page: https://github.com/shakelab/shakelab
Author: Valerio Poggi
Author-email: vpoggi@inogs.it
License: UNKNOWN
Platform: UNKNOWN
Classifier: Programming Language :: Python :: 3
Classifier: License :: OSI Approved :: GNU Affero General Public License v3
Classifier: Operating System :: OS Independent
Classifier: Topic :: Scientific/Engineering
Classifier: Intended Audience :: Science/Research
Requires-Python: >=3.6
License-File: LICENSE
Requires-Dist: setuptools
Requires-Dist: numpy
Requires-Dist: scipy
Requires-Dist: shapely
Requires-Dist: matplotlib
